vernex/__init__.py
vernex-0.0.1.dist-info/licenses/LICENSE
vernex-0.0.1.dist-info/METADATA
vernex-0.0.1.dist-info/WHEEL
vernex-0.0.1.dist-info/top_level.txt
vernex-0.0.1.dist-info/RECORD
