Metadata-Version: 2.4
Name: vernex
Version: 0.0.1
Summary: An intelligent coordination framework.
Author-email: Christopher Carr McMahon <CCarrMcMahon@gmail.com>
Maintainer-email: Christopher Carr McMahon <CCarrMcMahon@gmail.com>
License-Expression: MIT
Project-URL: Repository, https://github.com/CCarrMcMahon/vernex
Keywords: framework,development,workflow
Classifier: Development Status :: 1 - Planning
Classifier: Programming Language :: Python :: 3
Classifier: Programming Language :: Python :: 3.12
Requires-Python: >=3.12.10
License-File: LICENSE
Dynamic: license-file
